{"recenttracks":{"track":[{"artist":{"mbid":"66fc5bf8-daa4-4241-b378-9bc9077939d2","#text":"Tool"},"streamable":"0","image":[{"size":"small","#text":"https:\/\/lastfm.freetls.fastly.net\/i\/u\/34s\/61a415c9d77f0771717e82f10f62b099.jpg"},{"size":"medium","#text":"https:\/\/lastfm.freetls.fastly.net\/i\/u\/64s\/61a415c9d77f0771717e82f10f62b099.jpg"},{"size":"large","#text":"https:\/\/lastfm.freetls.fastly.net\/i\/u\/174s\/61a415c9d77f0771717e82f10f62b099.jpg"},{"size":"extralarge","#text":"https:\/\/lastfm.freetls.fastly.net\/i\/u\/300x300\/61a415c9d77f0771717e82f10f62b099.jpg"}],"mbid":"0a06d269-c055-43c6-b044-540d401c5dd2","album":{"mbid":"0e8c2238-3ead-434f-bb5e-d6b7e2fd2c64","#text":"Ænima"},"name":"Cesaro Summability","url":"https:\/\/www.last.fm\/music\/Tool\/_\/Cesaro+Summability","date":{"uts":"1740651016","#text":"27 Feb 2025, 10:10"}}],"@attr":{"user":"jsongif","totalPages":"1290","page":"1","perPage":"1","total":"1290"}}}