{"recenttracks":{"track":[{"artist":{"mbid":"f30f9355-4b0c-4c32-b28f-c0ef778a566e","#text":"Binary Star"},"streamable":"0","image":[{"size":"small","#text":"https:\/\/lastfm.freetls.fastly.net\/i\/u\/34s\/7fb72b3c3a8632226d51528e52ef7827.jpg"},{"size":"medium","#text":"https:\/\/lastfm.freetls.fastly.net\/i\/u\/64s\/7fb72b3c3a8632226d51528e52ef7827.jpg"},{"size":"large","#text":"https:\/\/lastfm.freetls.fastly.net\/i\/u\/174s\/7fb72b3c3a8632226d51528e52ef7827.jpg"},{"size":"extralarge","#text":"https:\/\/lastfm.freetls.fastly.net\/i\/u\/300x300\/7fb72b3c3a8632226d51528e52ef7827.jpg"}],"mbid":"","album":{"mbid":"6892e482-a100-4656-b261-289d638e7065","#text":"Masters of the Universe"},"name":"Glen Close (Feat. One Be Lo)","@attr":{"nowplaying":"true"},"url":"https:\/\/www.last.fm\/music\/Binary+Star\/_\/Glen+Close+(Feat.+One+Be+Lo)"},{"artist":{"mbid":"9b58e361-c3ba-41bb-b35f-edbcc1c96c82","#text":"Gene Harris & The Three Sounds"},"streamable":"0","image":[{"size":"small","#text":"https:\/\/lastfm.freetls.fastly.net\/i\/u\/34s\/2ccc901653b26b7490b4c63bfebe99d4.jpg"},{"size":"medium","#text":"https:\/\/lastfm.freetls.fastly.net\/i\/u\/64s\/2ccc901653b26b7490b4c63bfebe99d4.jpg"},{"size":"large","#text":"https:\/\/lastfm.freetls.fastly.net\/i\/u\/174s\/2ccc901653b26b7490b4c63bfebe99d4.jpg"},{"size":"extralarge","#text":"https:\/\/lastfm.freetls.fastly.net\/i\/u\/300x300\/2ccc901653b26b7490b4c63bfebe99d4.jpg"}],"mbid":"c37d9861-e6f8-3d39-bdc6-8a8ee03d61b6","album":{"mbid":"","#text":"Elegant Soul (Reissue)"},"name":"Book of Slim","url":"https:\/\/www.last.fm\/music\/Gene+Harris+&+The+Three+Sounds\/_\/Book+of+Slim","date":{"uts":"1764258055","#text":"27 Nov 2025, 15:40"}}],"@attr":{"user":"jsongif","totalPages":"21603","page":"1","perPage":"1","total":"21603"}}}