{"recenttracks":{"track":[{"artist":{"mbid":"d7bb5565-08e9-41f1-b138-c54724b29648","#text":"Lynnic"},"streamable":"0","image":[{"size":"small","#text":"https:\/\/lastfm.freetls.fastly.net\/i\/u\/34s\/ec184e67b3c18a5beec175a189977d68.jpg"},{"size":"medium","#text":"https:\/\/lastfm.freetls.fastly.net\/i\/u\/64s\/ec184e67b3c18a5beec175a189977d68.jpg"},{"size":"large","#text":"https:\/\/lastfm.freetls.fastly.net\/i\/u\/174s\/ec184e67b3c18a5beec175a189977d68.jpg"},{"size":"extralarge","#text":"https:\/\/lastfm.freetls.fastly.net\/i\/u\/300x300\/ec184e67b3c18a5beec175a189977d68.jpg"}],"mbid":"","album":{"mbid":"","#text":"Maze Of Memories"},"name":"Maze Of Memories","@attr":{"nowplaying":"true"},"url":"https:\/\/www.last.fm\/music\/Lynnic\/_\/Maze+Of+Memories"},{"artist":{"mbid":"07876ad1-652e-42fc-9c04-a904305c1173","#text":"Kaleida"},"streamable":"0","image":[{"size":"small","#text":"https:\/\/lastfm.freetls.fastly.net\/i\/u\/34s\/42d84bd9573c93c4f0ab073134cf041e.png"},{"size":"medium","#text":"https:\/\/lastfm.freetls.fastly.net\/i\/u\/64s\/42d84bd9573c93c4f0ab073134cf041e.png"},{"size":"large","#text":"https:\/\/lastfm.freetls.fastly.net\/i\/u\/174s\/42d84bd9573c93c4f0ab073134cf041e.png"},{"size":"extralarge","#text":"https:\/\/lastfm.freetls.fastly.net\/i\/u\/300x300\/42d84bd9573c93c4f0ab073134cf041e.png"}],"mbid":"89459802-5eec-4d40-8ab6-eec9d62ed244","album":{"mbid":"","#text":"Think (Anniversary Edition)"},"name":"TROPEA","url":"https:\/\/www.last.fm\/music\/Kaleida\/_\/TROPEA","date":{"uts":"1753103588","#text":"21 Jul 2025, 13:13"}}],"@attr":{"user":"jsongif","totalPages":"9857","page":"1","perPage":"1","total":"9857"}}}