{"recenttracks":{"track":[{"artist":{"mbid":"ee268c42-4b37-40e0-9da7-7bceb6c1bc8e","#text":"Sero"},"streamable":"0","image":[{"size":"small","#text":"https:\/\/lastfm.freetls.fastly.net\/i\/u\/34s\/2a96cbd8b46e442fc41c2b86b821562f.png"},{"size":"medium","#text":"https:\/\/lastfm.freetls.fastly.net\/i\/u\/64s\/2a96cbd8b46e442fc41c2b86b821562f.png"},{"size":"large","#text":"https:\/\/lastfm.freetls.fastly.net\/i\/u\/174s\/2a96cbd8b46e442fc41c2b86b821562f.png"},{"size":"extralarge","#text":"https:\/\/lastfm.freetls.fastly.net\/i\/u\/300x300\/2a96cbd8b46e442fc41c2b86b821562f.png"}],"mbid":"","album":{"mbid":"","#text":"Minute Sun"},"name":"Forest Sun","@attr":{"nowplaying":"true"},"url":"https:\/\/www.last.fm\/music\/Sero\/_\/Forest+Sun"},{"artist":{"mbid":"","#text":"Phfat"},"streamable":"0","image":[{"size":"small","#text":"https:\/\/lastfm.freetls.fastly.net\/i\/u\/34s\/2a96cbd8b46e442fc41c2b86b821562f.png"},{"size":"medium","#text":"https:\/\/lastfm.freetls.fastly.net\/i\/u\/64s\/2a96cbd8b46e442fc41c2b86b821562f.png"},{"size":"large","#text":"https:\/\/lastfm.freetls.fastly.net\/i\/u\/174s\/2a96cbd8b46e442fc41c2b86b821562f.png"},{"size":"extralarge","#text":"https:\/\/lastfm.freetls.fastly.net\/i\/u\/300x300\/2a96cbd8b46e442fc41c2b86b821562f.png"}],"mbid":"","album":{"mbid":"","#text":"Love & Death"},"name":"Do You Wanna Be Alone?","url":"https:\/\/www.last.fm\/music\/Phfat\/_\/Do+You+Wanna+Be+Alone%3F","date":{"uts":"1764057286","#text":"25 Nov 2025, 07:54"}}],"@attr":{"user":"jsongif","totalPages":"21294","page":"1","perPage":"1","total":"21294"}}}