{"recenttracks":{"track":[{"artist":{"mbid":"8f6bd1e4-fbe1-4f50-aa9b-94c450ec0f11","#text":"Portishead"},"streamable":"0","image":[{"size":"small","#text":"https:\/\/lastfm.freetls.fastly.net\/i\/u\/34s\/97c5cdebf17930906b4c3d26598c6192.jpg"},{"size":"medium","#text":"https:\/\/lastfm.freetls.fastly.net\/i\/u\/64s\/97c5cdebf17930906b4c3d26598c6192.jpg"},{"size":"large","#text":"https:\/\/lastfm.freetls.fastly.net\/i\/u\/174s\/97c5cdebf17930906b4c3d26598c6192.jpg"},{"size":"extralarge","#text":"https:\/\/lastfm.freetls.fastly.net\/i\/u\/300x300\/97c5cdebf17930906b4c3d26598c6192.jpg"}],"mbid":"8c023286-0509-4306-b173-d6646421ba34","album":{"mbid":"213910e7-279a-3186-81ae-cf330ded96fb","#text":"Roseland NYC Live"},"name":"Glory Box (Live)","url":"https:\/\/www.last.fm\/music\/Portishead\/_\/Glory+Box+(Live)","date":{"uts":"1737799094","#text":"25 Jan 2025, 09:58"}}],"@attr":{"user":"jsongif","totalPages":"69","page":"1","perPage":"1","total":"69"}}}