{"recenttracks":{"track":[{"artist":{"mbid":"02c9c7a0-58d4-4ac0-8130-72b4088a0e8a","#text":"DL Incognito"},"streamable":"0","image":[{"size":"small","#text":"https:\/\/lastfm.freetls.fastly.net\/i\/u\/34s\/7112c55e0c864004b61033d2e2ebb384.jpg"},{"size":"medium","#text":"https:\/\/lastfm.freetls.fastly.net\/i\/u\/64s\/7112c55e0c864004b61033d2e2ebb384.jpg"},{"size":"large","#text":"https:\/\/lastfm.freetls.fastly.net\/i\/u\/174s\/7112c55e0c864004b61033d2e2ebb384.jpg"},{"size":"extralarge","#text":"https:\/\/lastfm.freetls.fastly.net\/i\/u\/300x300\/7112c55e0c864004b61033d2e2ebb384.jpg"}],"mbid":"","album":{"mbid":"","#text":"Someday is Less Than a Second Away"},"name":"Days Gone","url":"https:\/\/www.last.fm\/music\/DL+Incognito\/_\/Days+Gone","date":{"uts":"1775051098","#text":"01 Apr 2026, 13:44"}}],"@attr":{"user":"jsongif","totalPages":"29173","page":"1","perPage":"1","total":"29173"}}}