{"recenttracks":{"track":[{"artist":{"mbid":"44cf61b8-5197-448a-b82b-cef6ee89fac5","#text":"Paramore"},"streamable":"0","image":[{"size":"small","#text":"https:\/\/lastfm.freetls.fastly.net\/i\/u\/34s\/fc4c4f4eb4fa6e9215ecb6705cbb72de.png"},{"size":"medium","#text":"https:\/\/lastfm.freetls.fastly.net\/i\/u\/64s\/fc4c4f4eb4fa6e9215ecb6705cbb72de.png"},{"size":"large","#text":"https:\/\/lastfm.freetls.fastly.net\/i\/u\/174s\/fc4c4f4eb4fa6e9215ecb6705cbb72de.png"},{"size":"extralarge","#text":"https:\/\/lastfm.freetls.fastly.net\/i\/u\/300x300\/fc4c4f4eb4fa6e9215ecb6705cbb72de.png"}],"mbid":"1295ef5a-3f6a-441b-a496-f393f3a3f792","album":{"mbid":"1080af22-6a39-45a0-9762-b1e9dfcfe642","#text":"After Laughter"},"name":"Hard Times","@attr":{"nowplaying":"true"},"url":"https:\/\/www.last.fm\/music\/Paramore\/_\/Hard+Times"},{"artist":{"mbid":"","#text":"The Avalanches"},"streamable":"0","image":[{"size":"small","#text":"https:\/\/lastfm.freetls.fastly.net\/i\/u\/34s\/79f7b18fab9b9298b93b31296dfb9b09.jpg"},{"size":"medium","#text":"https:\/\/lastfm.freetls.fastly.net\/i\/u\/64s\/79f7b18fab9b9298b93b31296dfb9b09.jpg"},{"size":"large","#text":"https:\/\/lastfm.freetls.fastly.net\/i\/u\/174s\/79f7b18fab9b9298b93b31296dfb9b09.jpg"},{"size":"extralarge","#text":"https:\/\/lastfm.freetls.fastly.net\/i\/u\/300x300\/79f7b18fab9b9298b93b31296dfb9b09.jpg"}],"mbid":"044802ec-5cf4-4222-a641-975c5f01b0c1","album":{"mbid":"086fc13b-ae2a-4867-97fb-2e055255b24a","#text":"Wildflower"},"name":"Because I'm Me","url":"https:\/\/www.last.fm\/music\/The+Avalanches\/_\/Because+I%27m+Me","date":{"uts":"1753976023","#text":"31 Jul 2025, 15:33"}}],"@attr":{"user":"jsongif","totalPages":"10373","page":"1","perPage":"1","total":"10373"}}}