{"recenttracks":{"track":[{"artist":{"mbid":"","#text":"Dillon Cooper"},"streamable":"0","image":[{"size":"small","#text":"https:\/\/lastfm.freetls.fastly.net\/i\/u\/34s\/2a96cbd8b46e442fc41c2b86b821562f.png"},{"size":"medium","#text":"https:\/\/lastfm.freetls.fastly.net\/i\/u\/64s\/2a96cbd8b46e442fc41c2b86b821562f.png"},{"size":"large","#text":"https:\/\/lastfm.freetls.fastly.net\/i\/u\/174s\/2a96cbd8b46e442fc41c2b86b821562f.png"},{"size":"extralarge","#text":"https:\/\/lastfm.freetls.fastly.net\/i\/u\/300x300\/2a96cbd8b46e442fc41c2b86b821562f.png"}],"mbid":"","album":{"mbid":"","#text":"D.O.G.G. - EP"},"name":"Dun-Money","@attr":{"nowplaying":"true"},"url":"https:\/\/www.last.fm\/music\/Dillon+Cooper\/_\/Dun-Money"},{"artist":{"mbid":"3808605b-4ee0-4514-a5a0-ac57ef9d511e","#text":"Kno"},"streamable":"0","image":[{"size":"small","#text":"https:\/\/lastfm.freetls.fastly.net\/i\/u\/34s\/632631693bae6b0260d8857d2e59a5dc.jpg"},{"size":"medium","#text":"https:\/\/lastfm.freetls.fastly.net\/i\/u\/64s\/632631693bae6b0260d8857d2e59a5dc.jpg"},{"size":"large","#text":"https:\/\/lastfm.freetls.fastly.net\/i\/u\/174s\/632631693bae6b0260d8857d2e59a5dc.jpg"},{"size":"extralarge","#text":"https:\/\/lastfm.freetls.fastly.net\/i\/u\/300x300\/632631693bae6b0260d8857d2e59a5dc.jpg"}],"mbid":"","album":{"mbid":"65ee731c-5c3c-47e9-a324-dcf9ac6aeac7","#text":"Death Is Silent"},"name":"Loneliness","url":"https:\/\/www.last.fm\/music\/Kno\/_\/Loneliness","date":{"uts":"1775562593","#text":"07 Apr 2026, 11:49"}}],"@attr":{"user":"jsongif","totalPages":"29269","page":"1","perPage":"1","total":"29269"}}}