{"recenttracks":{"track":[{"artist":{"mbid":"","#text":"Patrik Andrén"},"streamable":"0","image":[{"size":"small","#text":"https:\/\/lastfm.freetls.fastly.net\/i\/u\/34s\/f4de94a9bd0028441ecb830ea208a276.jpg"},{"size":"medium","#text":"https:\/\/lastfm.freetls.fastly.net\/i\/u\/64s\/f4de94a9bd0028441ecb830ea208a276.jpg"},{"size":"large","#text":"https:\/\/lastfm.freetls.fastly.net\/i\/u\/174s\/f4de94a9bd0028441ecb830ea208a276.jpg"},{"size":"extralarge","#text":"https:\/\/lastfm.freetls.fastly.net\/i\/u\/300x300\/f4de94a9bd0028441ecb830ea208a276.jpg"}],"mbid":"","album":{"mbid":"","#text":"Themes from ARC Raiders (Original Video Game Soundtrack)"},"name":"ARC Raiders","url":"https:\/\/www.last.fm\/music\/Patrik+Andr%C3%A9n\/_\/ARC+Raiders","date":{"uts":"1770364711","#text":"06 Feb 2026, 07:58"}}],"@attr":{"user":"jsongif","totalPages":"25623","page":"1","perPage":"1","total":"25623"}}}