{"recenttracks":{"track":[{"artist":{"mbid":"e731ab08-45c4-4e98-a1e4-7a16462c9cfb","#text":"WhoMadeWho"},"streamable":"0","image":[{"size":"small","#text":"https:\/\/lastfm.freetls.fastly.net\/i\/u\/34s\/8635aa158f05c79a1b1a6ee80c354951.jpg"},{"size":"medium","#text":"https:\/\/lastfm.freetls.fastly.net\/i\/u\/64s\/8635aa158f05c79a1b1a6ee80c354951.jpg"},{"size":"large","#text":"https:\/\/lastfm.freetls.fastly.net\/i\/u\/174s\/8635aa158f05c79a1b1a6ee80c354951.jpg"},{"size":"extralarge","#text":"https:\/\/lastfm.freetls.fastly.net\/i\/u\/300x300\/8635aa158f05c79a1b1a6ee80c354951.jpg"}],"mbid":"","album":{"mbid":"d1a68c88-5fc2-423b-b30f-09311f865e71","#text":"I Don't Know"},"name":"I Don't Know - Single Version","url":"https:\/\/www.last.fm\/music\/WhoMadeWho\/_\/I+Don%27t+Know+-+Single+Version","date":{"uts":"1755776893","#text":"21 Aug 2025, 11:48"}}],"@attr":{"user":"jsongif","totalPages":"11710","page":"1","perPage":"1","total":"11710"}}}