{"recenttracks":{"track":[{"artist":{"mbid":"65f4f0c5-ef9e-490c-aee3-909e7ae6b2ab","#text":"Metallica"},"streamable":"0","image":[{"size":"small","#text":"https:\/\/lastfm.freetls.fastly.net\/i\/u\/34s\/9c85d1a2416bbd2275026a8baa67cdf4.jpg"},{"size":"medium","#text":"https:\/\/lastfm.freetls.fastly.net\/i\/u\/64s\/9c85d1a2416bbd2275026a8baa67cdf4.jpg"},{"size":"large","#text":"https:\/\/lastfm.freetls.fastly.net\/i\/u\/174s\/9c85d1a2416bbd2275026a8baa67cdf4.jpg"},{"size":"extralarge","#text":"https:\/\/lastfm.freetls.fastly.net\/i\/u\/300x300\/9c85d1a2416bbd2275026a8baa67cdf4.jpg"}],"mbid":"09c8eb75-76ea-4cb0-97b9-f510ccbedc67","album":{"mbid":"","#text":"…And Justice For All (Remastered)"},"name":"One","@attr":{"nowplaying":"true"},"url":"https:\/\/www.last.fm\/music\/Metallica\/_\/One"},{"artist":{"mbid":"eb872766-98f6-453d-883f-2ae908a18315","#text":"TV on the Radio"},"streamable":"0","image":[{"size":"small","#text":"https:\/\/lastfm.freetls.fastly.net\/i\/u\/34s\/db087930279745f387dd0f892b7d6a07.png"},{"size":"medium","#text":"https:\/\/lastfm.freetls.fastly.net\/i\/u\/64s\/db087930279745f387dd0f892b7d6a07.png"},{"size":"large","#text":"https:\/\/lastfm.freetls.fastly.net\/i\/u\/174s\/db087930279745f387dd0f892b7d6a07.png"},{"size":"extralarge","#text":"https:\/\/lastfm.freetls.fastly.net\/i\/u\/300x300\/db087930279745f387dd0f892b7d6a07.png"}],"mbid":"27214a53-8f61-47d6-9120-241b840af1f8","album":{"mbid":"0dcc8966-36f4-370e-9705-a843c3bbad43","#text":"Dear Science"},"name":"DLZ","url":"https:\/\/www.last.fm\/music\/TV+on+the+Radio\/_\/DLZ","date":{"uts":"1750700515","#text":"23 Jun 2025, 17:41"}}],"@attr":{"user":"jsongif","totalPages":"8850","page":"1","perPage":"1","total":"8850"}}}