{"recenttracks":{"track":[{"artist":{"mbid":"b7539c32-53e7-4908-bda3-81449c367da6","#text":"Lana Del Rey"},"streamable":"0","image":[{"size":"small","#text":"https:\/\/lastfm.freetls.fastly.net\/i\/u\/34s\/9e9ddd9e9270cd400fcf60ab3d9fb1cc.jpg"},{"size":"medium","#text":"https:\/\/lastfm.freetls.fastly.net\/i\/u\/64s\/9e9ddd9e9270cd400fcf60ab3d9fb1cc.jpg"},{"size":"large","#text":"https:\/\/lastfm.freetls.fastly.net\/i\/u\/174s\/9e9ddd9e9270cd400fcf60ab3d9fb1cc.jpg"},{"size":"extralarge","#text":"https:\/\/lastfm.freetls.fastly.net\/i\/u\/300x300\/9e9ddd9e9270cd400fcf60ab3d9fb1cc.jpg"}],"mbid":"9d4dce87-85d2-4a7a-9b00-6322bec67a75","album":{"mbid":"00d42a8c-af17-46c3-a20f-f439b46ffe77","#text":"Lust for Life"},"name":"Lust for Life (with The Weeknd)","@attr":{"nowplaying":"true"},"url":"https:\/\/www.last.fm\/music\/Lana+Del+Rey\/_\/Lust+for+Life+(with+The+Weeknd)"},{"artist":{"mbid":"48262e82-db9f-4a92-b650-dfef979b73ec","#text":"Future"},"streamable":"0","image":[{"size":"small","#text":"https:\/\/lastfm.freetls.fastly.net\/i\/u\/34s\/ceae37ad2d17e660620bb306d08ed903.jpg"},{"size":"medium","#text":"https:\/\/lastfm.freetls.fastly.net\/i\/u\/64s\/ceae37ad2d17e660620bb306d08ed903.jpg"},{"size":"large","#text":"https:\/\/lastfm.freetls.fastly.net\/i\/u\/174s\/ceae37ad2d17e660620bb306d08ed903.jpg"},{"size":"extralarge","#text":"https:\/\/lastfm.freetls.fastly.net\/i\/u\/300x300\/ceae37ad2d17e660620bb306d08ed903.jpg"}],"mbid":"","album":{"mbid":"7fc1089f-3ab1-4232-97a2-fe62f9ca9d7c","#text":"EVOL"},"name":"Low Life (feat. The Weeknd)","url":"https:\/\/www.last.fm\/music\/Future\/_\/Low+Life+(feat.+The+Weeknd)","date":{"uts":"1739554488","#text":"14 Feb 2025, 17:34"}}],"@attr":{"user":"jsongif","totalPages":"772","page":"1","perPage":"1","total":"772"}}}