{"recenttracks":{"track":[{"artist":{"mbid":"","#text":"France Gall"},"streamable":"0","image":[{"size":"small","#text":"https:\/\/lastfm.freetls.fastly.net\/i\/u\/34s\/6b169e419a4075cd5c338590c1dfa74e.jpg"},{"size":"medium","#text":"https:\/\/lastfm.freetls.fastly.net\/i\/u\/64s\/6b169e419a4075cd5c338590c1dfa74e.jpg"},{"size":"large","#text":"https:\/\/lastfm.freetls.fastly.net\/i\/u\/174s\/6b169e419a4075cd5c338590c1dfa74e.jpg"},{"size":"extralarge","#text":"https:\/\/lastfm.freetls.fastly.net\/i\/u\/300x300\/6b169e419a4075cd5c338590c1dfa74e.jpg"}],"mbid":"","album":{"mbid":"","#text":"France Gall (Remasterisé en 2004)"},"name":"La déclaration d'amour - Remasterisé en 2004","url":"https:\/\/www.last.fm\/music\/France+Gall\/_\/La+d%C3%A9claration+d%27amour+-+Remasteris%C3%A9+en+2004","date":{"uts":"1776177468","#text":"14 Apr 2026, 14:37"}}],"@attr":{"user":"jsongif","totalPages":"29833","page":"1","perPage":"1","total":"29833"}}}