{"recenttracks":{"track":[{"artist":{"mbid":"","#text":"Deities"},"streamable":"0","image":[{"size":"small","#text":"https:\/\/lastfm.freetls.fastly.net\/i\/u\/34s\/2a96cbd8b46e442fc41c2b86b821562f.png"},{"size":"medium","#text":"https:\/\/lastfm.freetls.fastly.net\/i\/u\/64s\/2a96cbd8b46e442fc41c2b86b821562f.png"},{"size":"large","#text":"https:\/\/lastfm.freetls.fastly.net\/i\/u\/174s\/2a96cbd8b46e442fc41c2b86b821562f.png"},{"size":"extralarge","#text":"https:\/\/lastfm.freetls.fastly.net\/i\/u\/300x300\/2a96cbd8b46e442fc41c2b86b821562f.png"}],"mbid":"","album":{"mbid":"","#text":"Black silk"},"name":"Black silk","@attr":{"nowplaying":"true"},"url":"https:\/\/www.last.fm\/music\/Deities\/_\/Black+silk"},{"artist":{"mbid":"","#text":"Golden Tbilisi"},"streamable":"0","image":[{"size":"small","#text":"https:\/\/lastfm.freetls.fastly.net\/i\/u\/34s\/2a96cbd8b46e442fc41c2b86b821562f.png"},{"size":"medium","#text":"https:\/\/lastfm.freetls.fastly.net\/i\/u\/64s\/2a96cbd8b46e442fc41c2b86b821562f.png"},{"size":"large","#text":"https:\/\/lastfm.freetls.fastly.net\/i\/u\/174s\/2a96cbd8b46e442fc41c2b86b821562f.png"},{"size":"extralarge","#text":"https:\/\/lastfm.freetls.fastly.net\/i\/u\/300x300\/2a96cbd8b46e442fc41c2b86b821562f.png"}],"mbid":"","album":{"mbid":"","#text":"Adige (Trap Remix)"},"name":"Adige - Trap Remix","url":"https:\/\/www.last.fm\/music\/Golden+Tbilisi\/_\/Adige+-+Trap+Remix","date":{"uts":"1764011886","#text":"24 Nov 2025, 19:18"}}],"@attr":{"user":"jsongif","totalPages":"21259","page":"1","perPage":"1","total":"21259"}}}