{"recenttracks":{"track":[{"artist":{"mbid":"","#text":"Robert D."},"streamable":"0","image":[{"size":"small","#text":"https:\/\/lastfm.freetls.fastly.net\/i\/u\/34s\/f46fec6458eedfe1fe54d2782564db51.jpg"},{"size":"medium","#text":"https:\/\/lastfm.freetls.fastly.net\/i\/u\/64s\/f46fec6458eedfe1fe54d2782564db51.jpg"},{"size":"large","#text":"https:\/\/lastfm.freetls.fastly.net\/i\/u\/174s\/f46fec6458eedfe1fe54d2782564db51.jpg"},{"size":"extralarge","#text":"https:\/\/lastfm.freetls.fastly.net\/i\/u\/300x300\/f46fec6458eedfe1fe54d2782564db51.jpg"}],"mbid":"","album":{"mbid":"","#text":"The Very Best of Sci-fi & Fantasy (From Sucker Punch to V for Vendetta) [Original Motion Picture Soundtrack]"},"name":"Clubbed to Death (From \"The Matrix\")","@attr":{"nowplaying":"true"},"url":"https:\/\/www.last.fm\/music\/Robert+D.\/_\/Clubbed+to+Death+(From+%22The+Matrix%22)"},{"artist":{"mbid":"8970d868-0723-483b-a75b-51088913d3d4","#text":"Moby"},"streamable":"0","image":[{"size":"small","#text":"https:\/\/lastfm.freetls.fastly.net\/i\/u\/34s\/645ef9545c4ac26bc61563ca7a2c0bf3.png"},{"size":"medium","#text":"https:\/\/lastfm.freetls.fastly.net\/i\/u\/64s\/645ef9545c4ac26bc61563ca7a2c0bf3.png"},{"size":"large","#text":"https:\/\/lastfm.freetls.fastly.net\/i\/u\/174s\/645ef9545c4ac26bc61563ca7a2c0bf3.png"},{"size":"extralarge","#text":"https:\/\/lastfm.freetls.fastly.net\/i\/u\/300x300\/645ef9545c4ac26bc61563ca7a2c0bf3.png"}],"mbid":"","album":{"mbid":"025d4f1a-2e0a-3e0e-9808-f91f77340cf4","#text":"Play"},"name":"Porcelain","url":"https:\/\/www.last.fm\/music\/Moby\/_\/Porcelain","date":{"uts":"1738007709","#text":"27 Jan 2025, 19:55"}}],"@attr":{"user":"jsongif","totalPages":"265","page":"1","perPage":"1","total":"265"}}}