{"recenttracks":{"track":[{"artist":{"mbid":"88927646-0c28-4b1b-a69e-cb33c400d650","#text":"Nation of Language"},"streamable":"0","image":[{"size":"small","#text":"https:\/\/lastfm.freetls.fastly.net\/i\/u\/34s\/d859356583c92f9727ba7eae17f7d1c8.jpg"},{"size":"medium","#text":"https:\/\/lastfm.freetls.fastly.net\/i\/u\/64s\/d859356583c92f9727ba7eae17f7d1c8.jpg"},{"size":"large","#text":"https:\/\/lastfm.freetls.fastly.net\/i\/u\/174s\/d859356583c92f9727ba7eae17f7d1c8.jpg"},{"size":"extralarge","#text":"https:\/\/lastfm.freetls.fastly.net\/i\/u\/300x300\/d859356583c92f9727ba7eae17f7d1c8.jpg"}],"mbid":"3b8baf93-47e6-4bd2-b537-b6ee3c88cf16","album":{"mbid":"716ebead-475d-4a6c-9393-e58a5a1ac1da","#text":"Strange Disciple"},"name":"Weak In Your Light","@attr":{"nowplaying":"true"},"url":"https:\/\/www.last.fm\/music\/Nation+of+Language\/_\/Weak+In+Your+Light"},{"artist":{"mbid":"","#text":"Blue in Tokio"},"streamable":"0","image":[{"size":"small","#text":"https:\/\/lastfm.freetls.fastly.net\/i\/u\/34s\/80bbc00080752ce2e2b8d295e258c822.jpg"},{"size":"medium","#text":"https:\/\/lastfm.freetls.fastly.net\/i\/u\/64s\/80bbc00080752ce2e2b8d295e258c822.jpg"},{"size":"large","#text":"https:\/\/lastfm.freetls.fastly.net\/i\/u\/174s\/80bbc00080752ce2e2b8d295e258c822.jpg"},{"size":"extralarge","#text":"https:\/\/lastfm.freetls.fastly.net\/i\/u\/300x300\/80bbc00080752ce2e2b8d295e258c822.jpg"}],"mbid":"","album":{"mbid":"","#text":"Dark Sky Nights"},"name":"Damned","url":"https:\/\/www.last.fm\/music\/Blue+in+Tokio\/_\/Damned","date":{"uts":"1766051739","#text":"18 Dec 2025, 09:55"}}],"@attr":{"user":"jsongif","totalPages":"22939","page":"1","perPage":"1","total":"22939"}}}