{"recenttracks":{"track":[{"artist":{"mbid":"a74b1b7f-71a5-4011-9441-d0b5e4122711","#text":"Radiohead"},"streamable":"0","image":[{"size":"small","#text":"https:\/\/lastfm.freetls.fastly.net\/i\/u\/34s\/131e3e85d45047e93ab77b422e591719.jpg"},{"size":"medium","#text":"https:\/\/lastfm.freetls.fastly.net\/i\/u\/64s\/131e3e85d45047e93ab77b422e591719.jpg"},{"size":"large","#text":"https:\/\/lastfm.freetls.fastly.net\/i\/u\/174s\/131e3e85d45047e93ab77b422e591719.jpg"},{"size":"extralarge","#text":"https:\/\/lastfm.freetls.fastly.net\/i\/u\/300x300\/131e3e85d45047e93ab77b422e591719.jpg"}],"mbid":"","album":{"mbid":"0b6b4ba0-d36f-47bd-b4ea-6a5b91842d29","#text":"OK Computer"},"name":"Exit Music (for a Film)","@attr":{"nowplaying":"true"},"url":"https:\/\/www.last.fm\/music\/Radiohead\/_\/Exit+Music+(for+a+Film)"},{"artist":{"mbid":"f59c5520-5f46-4d2c-b2c4-822eabf53419","#text":"Linkin Park"},"streamable":"0","image":[{"size":"small","#text":"https:\/\/lastfm.freetls.fastly.net\/i\/u\/34s\/2a3ab7d7e3155d3779e4997f5f23d0ef.jpg"},{"size":"medium","#text":"https:\/\/lastfm.freetls.fastly.net\/i\/u\/64s\/2a3ab7d7e3155d3779e4997f5f23d0ef.jpg"},{"size":"large","#text":"https:\/\/lastfm.freetls.fastly.net\/i\/u\/174s\/2a3ab7d7e3155d3779e4997f5f23d0ef.jpg"},{"size":"extralarge","#text":"https:\/\/lastfm.freetls.fastly.net\/i\/u\/300x300\/2a3ab7d7e3155d3779e4997f5f23d0ef.jpg"}],"mbid":"97eab96f-aba1-3d8c-8186-783ed7364745","album":{"mbid":"a41c04e9-136b-4ef0-8556-1abad0453a88","#text":"Meteora (Bonus Edition)"},"name":"Lying from You","url":"https:\/\/www.last.fm\/music\/Linkin+Park\/_\/Lying+from+You","date":{"uts":"1744555017","#text":"13 Apr 2025, 14:36"}}],"@attr":{"user":"jsongif","totalPages":"4424","page":"1","perPage":"1","total":"4424"}}}