{"recenttracks":{"track":[{"artist":{"mbid":"d1515727-4a93-4c0d-88cb-d7a9fce01879","#text":"Jamie xx"},"streamable":"0","image":[{"size":"small","#text":"https:\/\/lastfm.freetls.fastly.net\/i\/u\/34s\/53b409f62e3542cdc2e33f4a2521f72f.png"},{"size":"medium","#text":"https:\/\/lastfm.freetls.fastly.net\/i\/u\/64s\/53b409f62e3542cdc2e33f4a2521f72f.png"},{"size":"large","#text":"https:\/\/lastfm.freetls.fastly.net\/i\/u\/174s\/53b409f62e3542cdc2e33f4a2521f72f.png"},{"size":"extralarge","#text":"https:\/\/lastfm.freetls.fastly.net\/i\/u\/300x300\/53b409f62e3542cdc2e33f4a2521f72f.png"}],"mbid":"099808bb-c498-4a93-8870-ef9513bc4fa0","album":{"mbid":"504afe35-cb5b-42ba-b2c3-87e6d0c3438b","#text":"All Under One Roof Raving"},"name":"All Under One Roof Raving","@attr":{"nowplaying":"true"},"url":"https:\/\/www.last.fm\/music\/Jamie+xx\/_\/All+Under+One+Roof+Raving"},{"artist":{"mbid":"49f82dfb-4568-4776-ae34-c957e70a1a1d","#text":"Chief Kamachi"},"streamable":"0","image":[{"size":"small","#text":"https:\/\/lastfm.freetls.fastly.net\/i\/u\/34s\/7283d0089343eb7063d351c0ee4de63e.jpg"},{"size":"medium","#text":"https:\/\/lastfm.freetls.fastly.net\/i\/u\/64s\/7283d0089343eb7063d351c0ee4de63e.jpg"},{"size":"large","#text":"https:\/\/lastfm.freetls.fastly.net\/i\/u\/174s\/7283d0089343eb7063d351c0ee4de63e.jpg"},{"size":"extralarge","#text":"https:\/\/lastfm.freetls.fastly.net\/i\/u\/300x300\/7283d0089343eb7063d351c0ee4de63e.jpg"}],"mbid":"","album":{"mbid":"","#text":"Rise and Rhyme, Vol. 1"},"name":"Swift Angels","url":"https:\/\/www.last.fm\/music\/Chief+Kamachi\/_\/Swift+Angels","date":{"uts":"1749293649","#text":"07 Jun 2025, 10:54"}}],"@attr":{"user":"jsongif","totalPages":"7830","page":"1","perPage":"1","total":"7830"}}}