{"recenttracks":{"track":[{"artist":{"mbid":"31bcadcc-e1da-4cad-bec8-2f4f1d41b095","#text":"Meek Mill"},"streamable":"0","image":[{"size":"small","#text":"https:\/\/lastfm.freetls.fastly.net\/i\/u\/34s\/ab6439fc7d56403601624cf4e3b2f325.jpg"},{"size":"medium","#text":"https:\/\/lastfm.freetls.fastly.net\/i\/u\/64s\/ab6439fc7d56403601624cf4e3b2f325.jpg"},{"size":"large","#text":"https:\/\/lastfm.freetls.fastly.net\/i\/u\/174s\/ab6439fc7d56403601624cf4e3b2f325.jpg"},{"size":"extralarge","#text":"https:\/\/lastfm.freetls.fastly.net\/i\/u\/300x300\/ab6439fc7d56403601624cf4e3b2f325.jpg"}],"mbid":"","album":{"mbid":"f928a16f-9211-44bd-88e6-227df132d9e9","#text":"DC4"},"name":"You Know (feat. YFN Lucci)","@attr":{"nowplaying":"true"},"url":"https:\/\/www.last.fm\/music\/Meek+Mill\/_\/You+Know+(feat.+YFN+Lucci)"},{"artist":{"mbid":"b95ce3ff-3d05-4e87-9e01-c97b66af13d4","#text":"Eminem"},"streamable":"0","image":[{"size":"small","#text":"https:\/\/lastfm.freetls.fastly.net\/i\/u\/34s\/abc023c871d2af6e0d53d521cc2e2bad.jpg"},{"size":"medium","#text":"https:\/\/lastfm.freetls.fastly.net\/i\/u\/64s\/abc023c871d2af6e0d53d521cc2e2bad.jpg"},{"size":"large","#text":"https:\/\/lastfm.freetls.fastly.net\/i\/u\/174s\/abc023c871d2af6e0d53d521cc2e2bad.jpg"},{"size":"extralarge","#text":"https:\/\/lastfm.freetls.fastly.net\/i\/u\/300x300\/abc023c871d2af6e0d53d521cc2e2bad.jpg"}],"mbid":"","album":{"mbid":"","#text":"Music To Be Murdered By - Side B (Deluxe Edition)"},"name":"Zeus (feat. White Gold)","url":"https:\/\/www.last.fm\/music\/Eminem\/_\/Zeus+(feat.+White+Gold)","date":{"uts":"1741869774","#text":"13 Mar 2025, 12:42"}}],"@attr":{"user":"jsongif","totalPages":"2333","page":"1","perPage":"1","total":"2333"}}}