{"recenttracks":{"track":[{"artist":{"mbid":"","#text":"Isis"},"streamable":"0","image":[{"size":"small","#text":"https:\/\/lastfm.freetls.fastly.net\/i\/u\/34s\/7714f47afa9ec36485541f57638b1141.jpg"},{"size":"medium","#text":"https:\/\/lastfm.freetls.fastly.net\/i\/u\/64s\/7714f47afa9ec36485541f57638b1141.jpg"},{"size":"large","#text":"https:\/\/lastfm.freetls.fastly.net\/i\/u\/174s\/7714f47afa9ec36485541f57638b1141.jpg"},{"size":"extralarge","#text":"https:\/\/lastfm.freetls.fastly.net\/i\/u\/300x300\/7714f47afa9ec36485541f57638b1141.jpg"}],"mbid":"","album":{"mbid":"","#text":"Panopticon (Remastered)"},"name":"So Did We - Remastered","@attr":{"nowplaying":"true"},"url":"https:\/\/www.last.fm\/music\/Isis\/_\/So+Did+We+-+Remastered"},{"artist":{"mbid":"","#text":"Isis"},"streamable":"0","image":[{"size":"small","#text":"https:\/\/lastfm.freetls.fastly.net\/i\/u\/34s\/7714f47afa9ec36485541f57638b1141.jpg"},{"size":"medium","#text":"https:\/\/lastfm.freetls.fastly.net\/i\/u\/64s\/7714f47afa9ec36485541f57638b1141.jpg"},{"size":"large","#text":"https:\/\/lastfm.freetls.fastly.net\/i\/u\/174s\/7714f47afa9ec36485541f57638b1141.jpg"},{"size":"extralarge","#text":"https:\/\/lastfm.freetls.fastly.net\/i\/u\/300x300\/7714f47afa9ec36485541f57638b1141.jpg"}],"mbid":"","album":{"mbid":"","#text":"Panopticon (Remastered)"},"name":"Backlit - Remastered","url":"https:\/\/www.last.fm\/music\/Isis\/_\/Backlit+-+Remastered","date":{"uts":"1776428962","#text":"17 Apr 2026, 12:29"}}],"@attr":{"user":"jsongif","totalPages":"30081","page":"1","perPage":"1","total":"30081"}}}