{"recenttracks":{"track":[{"artist":{"mbid":"","#text":"Osman"},"streamable":"0","image":[{"size":"small","#text":"https:\/\/lastfm.freetls.fastly.net\/i\/u\/34s\/f96ee98d99f8aafc6220ab1439321be8.jpg"},{"size":"medium","#text":"https:\/\/lastfm.freetls.fastly.net\/i\/u\/64s\/f96ee98d99f8aafc6220ab1439321be8.jpg"},{"size":"large","#text":"https:\/\/lastfm.freetls.fastly.net\/i\/u\/174s\/f96ee98d99f8aafc6220ab1439321be8.jpg"},{"size":"extralarge","#text":"https:\/\/lastfm.freetls.fastly.net\/i\/u\/300x300\/f96ee98d99f8aafc6220ab1439321be8.jpg"}],"mbid":"","album":{"mbid":"","#text":"Hawse"},"name":"Hawse","url":"https:\/\/www.last.fm\/music\/Osman\/_\/Hawse","date":{"uts":"1762266393","#text":"04 Nov 2025, 14:26"}}],"@attr":{"user":"jsongif","totalPages":"19320","page":"1","perPage":"1","total":"19320"}}}