{"recenttracks":{"track":[{"artist":{"mbid":"","#text":"Caleb Bryant"},"streamable":"0","image":[{"size":"small","#text":"https:\/\/lastfm.freetls.fastly.net\/i\/u\/34s\/545456a008ead4b052c1aa9754ef0b33.jpg"},{"size":"medium","#text":"https:\/\/lastfm.freetls.fastly.net\/i\/u\/64s\/545456a008ead4b052c1aa9754ef0b33.jpg"},{"size":"large","#text":"https:\/\/lastfm.freetls.fastly.net\/i\/u\/174s\/545456a008ead4b052c1aa9754ef0b33.jpg"},{"size":"extralarge","#text":"https:\/\/lastfm.freetls.fastly.net\/i\/u\/300x300\/545456a008ead4b052c1aa9754ef0b33.jpg"}],"mbid":"","album":{"mbid":"","#text":"The Fallen"},"name":"The Fallen","@attr":{"nowplaying":"true"},"url":"https:\/\/www.last.fm\/music\/Caleb+Bryant\/_\/The+Fallen"},{"artist":{"mbid":"","#text":"J. Ralph"},"streamable":"0","image":[{"size":"small","#text":"https:\/\/lastfm.freetls.fastly.net\/i\/u\/34s\/5a1e867834038001b93345427d3e93db.jpg"},{"size":"medium","#text":"https:\/\/lastfm.freetls.fastly.net\/i\/u\/64s\/5a1e867834038001b93345427d3e93db.jpg"},{"size":"large","#text":"https:\/\/lastfm.freetls.fastly.net\/i\/u\/174s\/5a1e867834038001b93345427d3e93db.jpg"},{"size":"extralarge","#text":"https:\/\/lastfm.freetls.fastly.net\/i\/u\/300x300\/5a1e867834038001b93345427d3e93db.jpg"}],"mbid":"","album":{"mbid":"","#text":"Racing Extinction (Original Motion Picture Soundtrack)"},"name":"Manta Ray","url":"https:\/\/www.last.fm\/music\/J.+Ralph\/_\/Manta+Ray","date":{"uts":"1753802292","#text":"29 Jul 2025, 15:18"}}],"@attr":{"user":"jsongif","totalPages":"10235","page":"1","perPage":"1","total":"10235"}}}