{"recenttracks":{"track":[{"artist":{"mbid":"2f83a35d-dd2d-46bc-a5a8-699de950f929","#text":"Hello Morning"},"streamable":"0","image":[{"size":"small","#text":"https:\/\/lastfm.freetls.fastly.net\/i\/u\/34s\/9a7492b371f14dc4a603e3d9becb595c.jpg"},{"size":"medium","#text":"https:\/\/lastfm.freetls.fastly.net\/i\/u\/64s\/9a7492b371f14dc4a603e3d9becb595c.jpg"},{"size":"large","#text":"https:\/\/lastfm.freetls.fastly.net\/i\/u\/174s\/9a7492b371f14dc4a603e3d9becb595c.jpg"},{"size":"extralarge","#text":"https:\/\/lastfm.freetls.fastly.net\/i\/u\/300x300\/9a7492b371f14dc4a603e3d9becb595c.jpg"}],"mbid":"","album":{"mbid":"","#text":"A Fiction"},"name":"Channels (One Thing)","url":"https:\/\/www.last.fm\/music\/Hello+Morning\/_\/Channels+(One+Thing)","date":{"uts":"1756362335","#text":"28 Aug 2025, 06:25"}}],"@attr":{"user":"jsongif","totalPages":"12111","page":"1","perPage":"1","total":"12111"}}}