{"recenttracks":{"track":[{"artist":{"mbid":"66fc5bf8-daa4-4241-b378-9bc9077939d2","#text":"Tool"},"streamable":"0","image":[{"size":"small","#text":"https:\/\/lastfm.freetls.fastly.net\/i\/u\/34s\/7840c5a71ebd451e8a923ae09de91785.png"},{"size":"medium","#text":"https:\/\/lastfm.freetls.fastly.net\/i\/u\/64s\/7840c5a71ebd451e8a923ae09de91785.png"},{"size":"large","#text":"https:\/\/lastfm.freetls.fastly.net\/i\/u\/174s\/7840c5a71ebd451e8a923ae09de91785.png"},{"size":"extralarge","#text":"https:\/\/lastfm.freetls.fastly.net\/i\/u\/300x300\/7840c5a71ebd451e8a923ae09de91785.png"}],"mbid":"839908af-0367-49b7-8795-2bf0f8e2dd61","album":{"mbid":"10aeb19a-d352-4b69-ba37-5a6e58dd2dda","#text":"10,000 Days"},"name":"The Pot","@attr":{"nowplaying":"true"},"url":"https:\/\/www.last.fm\/music\/Tool\/_\/The+Pot"},{"artist":{"mbid":"35966c6b-009b-4603-a4b4-fe2639c39f94","#text":"Cypis"},"streamable":"0","image":[{"size":"small","#text":"https:\/\/lastfm.freetls.fastly.net\/i\/u\/34s\/9d0b8bd0b46dc15956c83ba62900f74f.gif"},{"size":"medium","#text":"https:\/\/lastfm.freetls.fastly.net\/i\/u\/64s\/9d0b8bd0b46dc15956c83ba62900f74f.gif"},{"size":"large","#text":"https:\/\/lastfm.freetls.fastly.net\/i\/u\/174s\/9d0b8bd0b46dc15956c83ba62900f74f.gif"},{"size":"extralarge","#text":"https:\/\/lastfm.freetls.fastly.net\/i\/u\/300x300\/9d0b8bd0b46dc15956c83ba62900f74f.gif"}],"mbid":"f4fa9975-a99e-46b7-bd00-4801b344be1f","album":{"mbid":"","#text":"Gdzie jest biały węgorz (Zejście)"},"name":"Gdzie jest biały węgorz (Zejście)","url":"https:\/\/www.last.fm\/music\/Cypis\/_\/Gdzie+jest+bia%C5%82y+w%C4%99gorz+(Zej%C5%9Bcie)","date":{"uts":"1740741229","#text":"28 Feb 2025, 11:13"}}],"@attr":{"user":"jsongif","totalPages":"1362","page":"1","perPage":"1","total":"1362"}}}