{"recenttracks":{"track":[{"artist":{"mbid":"","#text":"Drake"},"streamable":"0","image":[{"size":"small","#text":"https:\/\/lastfm.freetls.fastly.net\/i\/u\/34s\/89117b736cebb7b4c129e37d3e94c340.jpg"},{"size":"medium","#text":"https:\/\/lastfm.freetls.fastly.net\/i\/u\/64s\/89117b736cebb7b4c129e37d3e94c340.jpg"},{"size":"large","#text":"https:\/\/lastfm.freetls.fastly.net\/i\/u\/174s\/89117b736cebb7b4c129e37d3e94c340.jpg"},{"size":"extralarge","#text":"https:\/\/lastfm.freetls.fastly.net\/i\/u\/300x300\/89117b736cebb7b4c129e37d3e94c340.jpg"}],"mbid":"0e08b1a7-1873-41a5-ad8d-2388f04a3de6","album":{"mbid":"26d2002d-cd52-4774-88f2-7ee6d4f53503","#text":"If You're Reading This It's Too Late"},"name":"6 Man","@attr":{"nowplaying":"true"},"url":"https:\/\/www.last.fm\/music\/Drake\/_\/6+Man"},{"artist":{"mbid":"","#text":"Kanye West"},"streamable":"0","image":[{"size":"small","#text":"https:\/\/lastfm.freetls.fastly.net\/i\/u\/34s\/32f2b94ebebb2742709006790b9209b9.png"},{"size":"medium","#text":"https:\/\/lastfm.freetls.fastly.net\/i\/u\/64s\/32f2b94ebebb2742709006790b9209b9.png"},{"size":"large","#text":"https:\/\/lastfm.freetls.fastly.net\/i\/u\/174s\/32f2b94ebebb2742709006790b9209b9.png"},{"size":"extralarge","#text":"https:\/\/lastfm.freetls.fastly.net\/i\/u\/300x300\/32f2b94ebebb2742709006790b9209b9.png"}],"mbid":"9058fc45-6396-435f-9e2e-be6511bbd23a","album":{"mbid":"23883c62-18b7-407b-a8d1-2c66cb58fb7a","#text":"Donda"},"name":"Praise God","url":"https:\/\/www.last.fm\/music\/Kanye+West\/_\/Praise+God","date":{"uts":"1754581445","#text":"07 Aug 2025, 15:44"}}],"@attr":{"user":"jsongif","totalPages":"10910","page":"1","perPage":"1","total":"10910"}}}