{"recenttracks":{"track":[{"artist":{"mbid":"589e6ebd-9896-4ca5-923a-14ee0845edbe","#text":"SUNDAZER"},"streamable":"0","image":[{"size":"small","#text":"https:\/\/lastfm.freetls.fastly.net\/i\/u\/34s\/82abd57b2eb332cda5dfa45d6bd50b34.png"},{"size":"medium","#text":"https:\/\/lastfm.freetls.fastly.net\/i\/u\/64s\/82abd57b2eb332cda5dfa45d6bd50b34.png"},{"size":"large","#text":"https:\/\/lastfm.freetls.fastly.net\/i\/u\/174s\/82abd57b2eb332cda5dfa45d6bd50b34.png"},{"size":"extralarge","#text":"https:\/\/lastfm.freetls.fastly.net\/i\/u\/300x300\/82abd57b2eb332cda5dfa45d6bd50b34.png"}],"mbid":"","album":{"mbid":"","#text":"Closer"},"name":"Closer","@attr":{"nowplaying":"true"},"url":"https:\/\/www.last.fm\/music\/SUNDAZER\/_\/Closer"},{"artist":{"mbid":"437d4038-0714-498d-b255-ead758d1a0e6","#text":"Imagine Music"},"streamable":"0","image":[{"size":"small","#text":"https:\/\/lastfm.freetls.fastly.net\/i\/u\/34s\/e1c70578231b267aa1cf4e1fd8d7b39e.jpg"},{"size":"medium","#text":"https:\/\/lastfm.freetls.fastly.net\/i\/u\/64s\/e1c70578231b267aa1cf4e1fd8d7b39e.jpg"},{"size":"large","#text":"https:\/\/lastfm.freetls.fastly.net\/i\/u\/174s\/e1c70578231b267aa1cf4e1fd8d7b39e.jpg"},{"size":"extralarge","#text":"https:\/\/lastfm.freetls.fastly.net\/i\/u\/300x300\/e1c70578231b267aa1cf4e1fd8d7b39e.jpg"}],"mbid":"","album":{"mbid":"","#text":"Supreme"},"name":"Doom","url":"https:\/\/www.last.fm\/music\/Imagine+Music\/_\/Doom","date":{"uts":"1751971553","#text":"08 Jul 2025, 10:45"}}],"@attr":{"user":"jsongif","totalPages":"9452","page":"1","perPage":"1","total":"9452"}}}