{"recenttracks":{"track":[{"artist":{"mbid":"dbbd3f1f-1c25-4dd6-b6d0-5a1bc7a3acc1","#text":"Klangkarussell"},"streamable":"0","image":[{"size":"small","#text":"https:\/\/lastfm.freetls.fastly.net\/i\/u\/34s\/b0d181404d454e1fcebaeb6f56574cc0.png"},{"size":"medium","#text":"https:\/\/lastfm.freetls.fastly.net\/i\/u\/64s\/b0d181404d454e1fcebaeb6f56574cc0.png"},{"size":"large","#text":"https:\/\/lastfm.freetls.fastly.net\/i\/u\/174s\/b0d181404d454e1fcebaeb6f56574cc0.png"},{"size":"extralarge","#text":"https:\/\/lastfm.freetls.fastly.net\/i\/u\/300x300\/b0d181404d454e1fcebaeb6f56574cc0.png"}],"mbid":"06b7de2f-16c2-46c1-bd2e-bf9ffa772f2b","album":{"mbid":"4cbf8d38-80b2-4081-b7f9-43327df497a5","#text":"Netzwerk"},"name":"Sternenkinder","url":"https:\/\/www.last.fm\/music\/Klangkarussell\/_\/Sternenkinder","date":{"uts":"1784376169","#text":"18 Jul 2026, 12:02"}}],"@attr":{"user":"jsongif","totalPages":"36168","page":"1","perPage":"1","total":"36168"}}}