{"recenttracks":{"track":[{"artist":{"mbid":"299278d3-25dd-4f30-bae4-5b571c28034d","#text":"The Postal Service"},"streamable":"0","image":[{"size":"small","#text":"https:\/\/lastfm.freetls.fastly.net\/i\/u\/34s\/c15892b07145e2beb960c264c6ad9974.jpg"},{"size":"medium","#text":"https:\/\/lastfm.freetls.fastly.net\/i\/u\/64s\/c15892b07145e2beb960c264c6ad9974.jpg"},{"size":"large","#text":"https:\/\/lastfm.freetls.fastly.net\/i\/u\/174s\/c15892b07145e2beb960c264c6ad9974.jpg"},{"size":"extralarge","#text":"https:\/\/lastfm.freetls.fastly.net\/i\/u\/300x300\/c15892b07145e2beb960c264c6ad9974.jpg"}],"mbid":"0cd29efb-f852-30a1-baa6-47b8afbc76ca","album":{"mbid":"00161f8c-f335-465d-a944-597d67616d9a","#text":"Give Up"},"name":"Sleeping In","@attr":{"nowplaying":"true"},"url":"https:\/\/www.last.fm\/music\/The+Postal+Service\/_\/Sleeping+In"},{"artist":{"mbid":"299278d3-25dd-4f30-bae4-5b571c28034d","#text":"The Postal Service"},"streamable":"0","image":[{"size":"small","#text":"https:\/\/lastfm.freetls.fastly.net\/i\/u\/34s\/c15892b07145e2beb960c264c6ad9974.jpg"},{"size":"medium","#text":"https:\/\/lastfm.freetls.fastly.net\/i\/u\/64s\/c15892b07145e2beb960c264c6ad9974.jpg"},{"size":"large","#text":"https:\/\/lastfm.freetls.fastly.net\/i\/u\/174s\/c15892b07145e2beb960c264c6ad9974.jpg"},{"size":"extralarge","#text":"https:\/\/lastfm.freetls.fastly.net\/i\/u\/300x300\/c15892b07145e2beb960c264c6ad9974.jpg"}],"mbid":"04c1bf65-9fcf-4cab-8edd-a41e042d5090","album":{"mbid":"00161f8c-f335-465d-a944-597d67616d9a","#text":"Give Up"},"name":"Such Great Heights","url":"https:\/\/www.last.fm\/music\/The+Postal+Service\/_\/Such+Great+Heights","date":{"uts":"1773066600","#text":"09 Mar 2026, 14:30"}}],"@attr":{"user":"jsongif","totalPages":"27389","page":"1","perPage":"1","total":"27389"}}}